MANIFEST.in
README.md
setup.py
geomepy/__init__.py
geomepy/analysis.py
geomepy/geomepy.py
geomepy/geometry.py
geomepy/tmp.py
geomepy.egg-info/PKG-INFO
geomepy.egg-info/SOURCES.txt
geomepy.egg-info/dependency_links.txt
geomepy.egg-info/entry_points.txt
geomepy.egg-info/requires.txt
geomepy.egg-info/top_level.txt